autoimpute/__init__.py
autoimpute/cross_val.py
autoimpute/evaluation.py
autoimpute/imputation.py
autoimpute/metrics.py
autoimpute/model_selection.py
autoimpute/models_imputation.py
autoimpute/multiple_imputation.py
autoimpute/parameters.py
autoimpute/visualization.py
autopieby2-1.0.82.dist-info/METADATA
autopieby2-1.0.82.dist-info/WHEEL
autopieby2-1.0.82.dist-info/top_level.txt
autopieby2-1.0.82.dist-info/RECORD
