Metadata-Version: 2.4
Name: autopieby2
Version: 1.0.82
Summary: AutoImpute - Missing Data Imputation Framework for Machine Learning
Home-page: https://github.com/pieby2/AutoImpute
Author: Prakhar
Author-email: Prakharpragyan1000@gmail.com
License: MIT
Keywords: data science,machine learning,data preprocessing,null imputation,predictive null imputation,multiple null imputation,automated machine learning
Classifier: Intended Audience :: Education
Classifier: Intended Audience :: Developers
Classifier: Intended Audience :: Science/Research
Classifier: Intended Audience :: Customer Service
Classifier: Intended Audience :: Financial and Insurance Industry
Classifier: Intended Audience :: Healthcare Industry
Classifier: Intended Audience :: Telecommunications Industry
Classifier: Topic :: Scientific/Engineering :: Artificial Intelligence
Classifier: Topic :: Scientific/Engineering :: Information Analysis
Classifier: License :: OSI Approved :: MIT License
Classifier: Operating System :: OS Independent
Classifier: Programming Language :: Python :: 3.8
Classifier: Programming Language :: Python :: 3.9
Classifier: Programming Language :: Python :: 3.10
Classifier: Programming Language :: Python :: 3.11
Requires-Python: >=3.8
Requires-Dist: atlantic>=1.1.80
Requires-Dist: catboost>=1.1.1
Requires-Dist: xgboost>=1.7.3
Requires-Dist: lightgbm>=3.3.5
Requires-Dist: matplotlib>=3.5.0
Requires-Dist: seaborn>=0.11.0
Dynamic: author
Dynamic: author-email
Dynamic: classifier
Dynamic: description
Dynamic: description-content-type
Dynamic: home-page
Dynamic: keywords
Dynamic: license
Dynamic: requires-dist
Dynamic: requires-python
Dynamic: summary
